Metadata-Version: 1.0
Name: tfnets
Version: 0.5
Summary: A library of common models implemented in tensorflow
Home-page: https://github.com/huyng/tfnets
Author: Huy Nguyen
Author-email: huy@huyng.com
License: UNKNOWN
Platform: UNKNOWN
